adios2py/__init__.py
adios2py/_version.py
adios2py/_version.pyi
adios2py/array_proxy.py
adios2py/attrs_proxy.py
adios2py/file.py
adios2py/group.py
adios2py/py.typed
adios2py/step.py
adios2py/steps_proxy.py
adios2py/util.py
adios2py-0.1.0a6.dist-info/LICENSE
adios2py-0.1.0a6.dist-info/METADATA
adios2py-0.1.0a6.dist-info/WHEEL
adios2py-0.1.0a6.dist-info/top_level.txt
adios2py-0.1.0a6.dist-info/RECORD
