Metadata-Version: 2.2
Name: adios2py
Version: 0.1.0a6
Summary: A pythonic interface to the ADIOS2 I/O library
Author-email: Kai Germaschewski <kai.germaschewski@unh.edu>
License: 
Project-URL: Homepage, https://github.com/unh-hpc/adios2py
Project-URL: Bug Tracker, https://github.com/unh-hpc/adios2py/issues
Project-URL: Discussions, https://github.com/unh-hpc/adios2py/discussions
Project-URL: Changelog, https://github.com/unh-hpc/adios2py/releases
Classifier: Development Status :: 1 - Planning
Classifier: Intended Audience :: Science/Research
Classifier: Intended Audience :: Developers
Classifier: License :: OSI Approved :: Apache Software License
Classifier: Operating System :: OS Independent
Classifier: Programming Language :: Python
Classifier: Programming Language :: Python :: 3
Classifier: Programming Language :: Python :: 3 :: Only
Classifier: Programming Language :: Python :: 3.10
Classifier: Programming Language :: Python :: 3.11
Classifier: Programming Language :: Python :: 3.12
Classifier: Programming Language :: Python :: 3.13
Classifier: Topic :: Scientific/Engineering
Classifier: Typing :: Typed
Requires-Python: >=3.10
License-File: LICENSE
Requires-Dist: adios2
Provides-Extra: test
Requires-Dist: pytest>=6; extra == "test"
Requires-Dist: pytest-cov>=3; extra == "test"
Provides-Extra: dev
Requires-Dist: pytest>=6; extra == "dev"
Requires-Dist: pytest-cov>=3; extra == "dev"
Requires-Dist: pre-commit; extra == "dev"
Requires-Dist: nox; extra == "dev"
Requires-Dist: mypy; extra == "dev"
Provides-Extra: docs
Requires-Dist: sphinx>=7.0; extra == "docs"
Requires-Dist: myst_parser>=0.13; extra == "docs"
Requires-Dist: sphinx_copybutton; extra == "docs"
Requires-Dist: sphinx_autodoc_typehints; extra == "docs"
Requires-Dist: furo>=2023.08.17; extra == "docs"
